luigi_tools/__init__.py
luigi_tools/parameter.py
luigi_tools/target.py
luigi_tools/task.py
luigi_tools/util.py
luigi_tools-0.3.5.dist-info/licenses/AUTHORS.md
luigi_tools-0.3.5.dist-info/licenses/LICENSE.txt
luigi_tools-0.3.5.dist-info/METADATA
luigi_tools-0.3.5.dist-info/WHEEL
luigi_tools-0.3.5.dist-info/top_level.txt
luigi_tools-0.3.5.dist-info/RECORD
