Metadata-Version: 2.4
Name: luigi-tools
Version: 0.3.5
Summary: Tools to work with luigi.
Home-page: https://luigi-tools.readthedocs.io
Author: Blue Brain Project, EPFL
License: Apache License 2.0
Project-URL: Tracker, https://github.com/BlueBrain/luigi-tools/issues
Project-URL: Source, https://github.com/BlueBrain/luigi-tools
Classifier: Development Status :: 4 - Beta
Classifier: Intended Audience :: Developers
Classifier: Intended Audience :: Science/Research
Classifier: License :: OSI Approved :: Apache Software License
Classifier: Programming Language :: Python
Classifier: Programming Language :: Python :: 3
Classifier: Programming Language :: Python :: 3.9
Classifier: Programming Language :: Python :: 3.10
Classifier: Programming Language :: Python :: 3.11
Classifier: Programming Language :: Python :: 3.12
Classifier: Topic :: Scientific/Engineering
Requires-Python: >=3.9
License-File: LICENSE.txt
License-File: AUTHORS.md
Requires-Dist: luigi>=3.1
Requires-Dist: jsonschema>=4.2
Requires-Dist: typing-extensions>=4
Provides-Extra: docs
Requires-Dist: docutils<0.21; extra == "docs"
Requires-Dist: m2r2; extra == "docs"
Requires-Dist: sphinx; extra == "docs"
Requires-Dist: sphinx-bluebrain-theme; extra == "docs"
Provides-Extra: graphviz
Requires-Dist: graphviz; extra == "graphviz"
Provides-Extra: test
Requires-Dist: mock>=3; extra == "test"
Requires-Dist: pytest>=8; extra == "test"
Requires-Dist: pytest-cov>=4.1; extra == "test"
Requires-Dist: pytest-html>=4; extra == "test"
Dynamic: author
Dynamic: classifier
Dynamic: description
Dynamic: description-content-type
Dynamic: home-page
Dynamic: license
Dynamic: license-file
Dynamic: project-url
Dynamic: provides-extra
Dynamic: requires-dist
Dynamic: requires-python
Dynamic: summary
